pypam/__init__.py
pypam/_event.py
pypam/acoustic_file.py
pypam/acoustic_indices.py
pypam/acoustic_survey.py
pypam/dataset.py
pypam/detection.py
pypam/plots.py
pypam/signal.py
pypam/units.py
pypam/utils.py
lifewatch_pypam-0.4.0.dist-info/LICENSE
lifewatch_pypam-0.4.0.dist-info/METADATA
lifewatch_pypam-0.4.0.dist-info/WHEEL
lifewatch_pypam-0.4.0.dist-info/RECORD
