Metadata-Version: 2.1
Name: lifewatch-pypam
Version: 0.4.0
Summary: Facilitate acoustic processing from underwater acoustic recorders
Home-page: https://github.com/lifewatch/pypam.git
License: GPL-3.0-or-later
Author: Clea Parcerisas
Author-email: cleap@vliz.be
Requires-Python: >=3.9,<3.13.0
Classifier: License :: OSI Approved :: GNU General Public License v3 or later (GPLv3+)
Classifier: License :: OSI Approved :: MIT License
Classifier: Operating System :: OS Independent
Classifier: Programming Language :: Python :: 3
Classifier: Programming Language :: Python :: 3.9
Classifier: Programming Language :: Python :: 3.10
Classifier: Programming Language :: Python :: 3.11
Classifier: Programming Language :: Python :: 3.12
Requires-Dist: dask (>=2023.0.0,<2024.0.0)
Requires-Dist: matplotlib (>=3.7.1,<4.0.0)
Requires-Dist: netcdf4 (>=1.6.4,<2.0.0)
Requires-Dist: noisereduce (>=2.0.1,<3.0.0)
Requires-Dist: numba (>=0.58)
Requires-Dist: numpy (<2.0)
Requires-Dist: openpyxl (>=3.1.5,<4.0.0)
Requires-Dist: pandas (>=2.0.2,<3.0.0)
Requires-Dist: pvlib (>=0.11.0,<0.12.0)
Requires-Dist: pyhydrophone (>=0.2.0)
Requires-Dist: python-dateutil (>=2.8.2,<3.0.0)
Requires-Dist: scikit-learn (>=1.2.2,<2.0.0)
Requires-Dist: scikit-maad (>=1.4.3,<2.0.0)
Requires-Dist: seaborn (==0.13.0)
Requires-Dist: soundfile (>=0.12.1,<0.13.0)
Requires-Dist: syrupy (>=4.0.4,<5.0.0)
Requires-Dist: tqdm (>=4.65.0,<5.0.0)
Requires-Dist: xarray (==2023.8.0)
Project-URL: Repository, https://github.com/lifewatch/pypam.git
